AUTHORS.rst
CONTRIBUTING.rst
HISTORY.rst
LICENSE
MANIFEST.in
README.rst
setup.cfg
setup.py
docs/Makefile
docs/authors.rst
docs/conf.py
docs/contributing.rst
docs/history.rst
docs/index.rst
docs/installation.rst
docs/make.bat
docs/readme.rst
docs/usage.rst
dpybrew/__init__.py
dpybrew/cli.py
dpybrew/dpybrew.py
dpybrew/extensions.py
dpybrew.egg-info/PKG-INFO
dpybrew.egg-info/SOURCES.txt
dpybrew.egg-info/dependency_links.txt
dpybrew.egg-info/entry_points.txt
dpybrew.egg-info/not-zip-safe
dpybrew.egg-info/requires.txt
dpybrew.egg-info/top_level.txt
dpybrew/service/__init__.py
dpybrew/service/pagenator.py
tests/__init__.py
tests/test_dpybrew.py