Metadata-Version: 1.2
Name: dpybrew
Version: 0.3.0
Summary: A discord.py extension/service manager
Home-page: https://github.com/sizumita/dpybrew
Author: sizumita
Author-email: 
License: MIT license
Keywords: dpybrew
Platform: UNKNOWN
Classifier: Development Status :: 2 - Pre-Alpha
Classifier: Intended Audience :: Developers
Classifier: License :: OSI Approved :: MIT License
Classifier: Natural Language :: English
Classifier: Programming Language :: Python :: 3.7
Classifier: Programming Language :: Python :: 3.8
Requires-Python: >=3.7
